odoo10_addon_super_calendar-10.0.1.0.0.99.dev3-py3.8-nspkg.pth
odoo/addons/super_calendar/README.rst
odoo/addons/super_calendar/__init__.py
odoo/addons/super_calendar/__manifest__.py
odoo/addons/super_calendar/data/cron_data.xml
odoo/addons/super_calendar/i18n/am.po
odoo/addons/super_calendar/i18n/ar.po
odoo/addons/super_calendar/i18n/bg.po
odoo/addons/super_calendar/i18n/bs.po
odoo/addons/super_calendar/i18n/ca.po
odoo/addons/super_calendar/i18n/cs.po
odoo/addons/super_calendar/i18n/da.po
odoo/addons/super_calendar/i18n/de.po
odoo/addons/super_calendar/i18n/el_GR.po
odoo/addons/super_calendar/i18n/en_GB.po
odoo/addons/super_calendar/i18n/es.po
odoo/addons/super_calendar/i18n/es_AR.po
odoo/addons/super_calendar/i18n/es_CO.po
odoo/addons/super_calendar/i18n/es_CR.po
odoo/addons/super_calendar/i18n/es_EC.po
odoo/addons/super_calendar/i18n/es_ES.po
odoo/addons/super_calendar/i18n/es_MX.po
odoo/addons/super_calendar/i18n/es_PE.po
odoo/addons/super_calendar/i18n/es_PY.po
odoo/addons/super_calendar/i18n/es_VE.po
odoo/addons/super_calendar/i18n/et.po
odoo/addons/super_calendar/i18n/fa.po
odoo/addons/super_calendar/i18n/fi.po
odoo/addons/super_calendar/i18n/fr.po
odoo/addons/super_calendar/i18n/fr_CA.po
odoo/addons/super_calendar/i18n/fr_CH.po
odoo/addons/super_calendar/i18n/gl.po
odoo/addons/super_calendar/i18n/gl_ES.po
odoo/addons/super_calendar/i18n/he.po
odoo/addons/super_calendar/i18n/hr.po
odoo/addons/super_calendar/i18n/hr_HR.po
odoo/addons/super_calendar/i18n/hu.po
odoo/addons/super_calendar/i18n/it.po
odoo/addons/super_calendar/i18n/ja.po
odoo/addons/super_calendar/i18n/ko.po
odoo/addons/super_calendar/i18n/lt.po
odoo/addons/super_calendar/i18n/lv.po
odoo/addons/super_calendar/i18n/mk.po
odoo/addons/super_calendar/i18n/mn.po
odoo/addons/super_calendar/i18n/nb.po
odoo/addons/super_calendar/i18n/nl.po
odoo/addons/super_calendar/i18n/nl_BE.po
odoo/addons/super_calendar/i18n/pl.po
odoo/addons/super_calendar/i18n/pt.po
odoo/addons/super_calendar/i18n/pt_BR.po
odoo10_addon_super_calendar-10.0.1.0.0.99.dev3.dist-info/METADATA
odoo10_addon_super_calendar-10.0.1.0.0.99.dev3.dist-info/WHEEL
odoo10_addon_super_calendar-10.0.1.0.0.99.dev3.dist-info/namespace_packages.txt
odoo10_addon_super_calendar-10.0.1.0.0.99.dev3.dist-info/top_level.txt
odoo10_addon_super_calendar-10.0.1.0.0.99.dev3.dist-info/RECORD
